.coveragerc
.travis.yml
AUTHORS
ChangeLog
LICENSE
README.rst
setup.cfg
setup.py
test-requirements.txt
pyhiccup/__init__.py
pyhiccup/core.py
pyhiccup/element.py
pyhiccup/page.py
pyhiccup.egg-info/PKG-INFO
pyhiccup.egg-info/SOURCES.txt
pyhiccup.egg-info/dependency_links.txt
pyhiccup.egg-info/not-zip-safe
pyhiccup.egg-info/top_level.txt
pyhiccup/tests/__init__.py
pyhiccup/tests/common.py
pyhiccup/tests/test_basic.py
pyhiccup/tests/test_element.py