Metadata-Version: 1.0
Name: pyhiccup
Version: 0.1
Summary: Library for representing HTML in Python
Home-page: http://pypi.python.org/pypi/pyhiccup
Author: Nicolas Bessi
Author-email: nbessi@gmail.com
License: GPL3
Platform: UNKNOWN
